image_padder/__init__.py
image_padder/main.py
image_padder-0.1.1.dist-info/METADATA
image_padder-0.1.1.dist-info/WHEEL
image_padder-0.1.1.dist-info/entry_points.txt
image_padder-0.1.1.dist-info/top_level.txt
image_padder-0.1.1.dist-info/RECORD
