Metadata-Version: 2.4
Name: image-padder
Version: 0.1.1
Summary: A command-line tool to pad and resize images
Home-page: https://github.com/crapthings/py-image-padder
Author: crapthings
Author-email: crapthings@gmail.com
Classifier: Programming Language :: Python :: 3
Classifier: License :: OSI Approved :: MIT License
Classifier: Operating System :: OS Independent
Requires-Python: >=3.6
Requires-Dist: Pillow
Requires-Dist: tqdm
Dynamic: author
Dynamic: author-email
Dynamic: classifier
Dynamic: description
Dynamic: description-content-type
Dynamic: home-page
Dynamic: requires-dist
Dynamic: requires-python
Dynamic: summary
